Workbook

Sheet Assumptions
A1: InvestiGate Unit Economics Model
A3: Input | B3: Value | C3: Units | D3: Notes
A4: OpenAI GPT-4o input price | B4: 2.5 | C4: $ / 1M tokens | D4: Current assumption for GPT-4o input pricing.
A5: OpenAI GPT-4o output price | B5: 10 | C5: $ / 1M tokens | D5: Current assumption for GPT-4o output pricing.
A6: Embedding price | B6: 0.02 | C6: $ / 1M tokens | D6: text-embedding-3-small assumption.
A7: Whisper transcription price | B7: 0.006 | C7: $ / minute | D7: whisper-1 assumption.
A8: Analyst calls per run | B8: 3 | C8: count | D8: Bull, Bear, Strategist.
A9: Judge calls per run | B9: 1 | C9: count | D9: One synthesis call.
A10: Analyst input tokens per call | B10: 7000 | C10: tokens | D10: Typical with market data + RAG context.
A11: Analyst output tokens per call | B11: 900 | C11: tokens | D11: Typical structured response size.
A12: Judge input tokens per call | B12: 9000 | C12: tokens | D12: Receives all three reports + market data + RAG.
A13: Judge output tokens per call | B13: 1500 | C13: tokens | D13: Recommendation + explanation.
A14: Fresh RAG embedding tokens | B14: 20000 | C14: tokens | D14: Cold ticker/day incremental embedding estimate.
A15: Voice query length | B15: 0.5 | C15: minutes | D15: 30 second recording.
... A26: Monthly active users | B26: 100 | C26: users | D26: Editable scale assumption.
A29: Check | B29: =SUM(B17:B21) | C29: Should equal 100% | D29: Run-mix sanity check.

Sheet Per Run Economics
A1: Per-Run Unit Economics
A3: Scenario | B3: LLM Text Cost | C3: Embedding Cost | D3: Voice Cost | E3: Total Variable Cost | F3: Notes
A4: Exact cache hit | B4: =0 | C4: =0 | D4: =0 | E4: =SUM(B4:D4) | F4: Identical query served from 5-minute result cache.
A5: Warm text analysis | B5: =(((Assumptions!B8*Assumptions!B10)+(Assumptions!B9*Assumptions!B12))*Assumptions!B4 + ((Assumptions!B8*Assumptions!B11)+(Assumptions!B9*Assumptions!B13))*Assumptions!B5)/1000000*(1+Assumptions!B16) | C5: =0 | D5: =0 | E5: =SUM(B5:D5) | F5: Fresh market fetch + fresh-enough RAG docs.
A6: Cold ticker/day analysis | B6: =B5 | C6: =Assumptions!B14*Assumptions!B6/1000000 | D6: =0 | E6: =SUM(B6:D6) | F6: Warm text path plus fresh embeddings for new/stale docs.
A7: Voice analysis | B7: =B5 | C7: =0 | D7: =Assumptions!B15*Assumptions!B7 | E7: =SUM(B7:D7) | F7: Warm text path plus transcription.
A8: Retry-heavy tail | B8: =B5*2.5 | C8: =C6 | D8: =0 | E8: =SUM(B8:D8) | F8: Tail case with multiple retries / longer outputs.
A11: Weighted average variable cost / run | B11: =SUMPRODUCT(E4:E8,Assumptions!B17:B21)
A12: Blended monthly analyses | B12: =Assumptions!B25*Assumptions!B26
A13: Blended monthly variable cost | B13: =B11*B12
A14: Total monthly fixed cost | B14: =Assumptions!B22+Assumptions!B23
A15: All-in monthly cost | B15: =B13+B14
A16: Revenue / month | B16: =Assumptions!B24*Assumptions!B26
A17: Gross profit / month | B17: =B16-B15
A18: Gross margin % | B18: =IFERROR(B17/B16,0)

Sheet Pricing Sensitivity
A1: Pricing and Usage Sensitivity
A3: Users \ Price | B3: 10 | C3: 15 | D3: 20 | E3: 25 | F3: 30
A4: 50 | B4: =IFERROR(((B3*A4)-(('Per Run Economics'!$B$11*Assumptions!$B$25*A4)+(Assumptions!$B$22+Assumptions!$B$23)))/(B3*A4),0) | C4: =IFERROR(((C3*A4)-(('Per Run Economics'!$B$11*Assumptions!$B$25*A4)+(Assumptions!$B$22+Assumptions!$B$23)))/(C3*A4),0) | D4: =IFERROR(((D3*A4)-(('Per Run Economics'!$B$11*Assumptions!$B$25*A4)+(Assumptions!$B$22+Assumptions!$B$23)))/(D3*A4),0) | E4: =IFERROR(((E3*A4)-(('Per Run Economics'!$B$11*Assumptions!$B$25*A4)+(Assumptions!$B$22+Assumptions!$B$23)))/(E3*A4),0) | F4: =IFERROR(((F3*A4)-(('Per Run Economics'!$B$11*Assumptions!$B$25*A4)+(Assumptions!$B$22+Assumptions!$B$23)))/(F3*A4),0)
A5: 100 | B5: =IFERROR(((B3*A5)-(('Per Run Economics'!$B$11*Assumptions!$B$25*A5)+(Assumptions!$B$22+Assumptions!$B$23)))/(B3*A5),0) | C5: =IFERROR(((C3*A5)-(('Per Run Economics'!$B$11*Assumptions!$B$25*A5)+(Assumptions!$B$22+Assumptions!$B$23)))/(C3*A5),0) | D5: =IFERROR(((D3*A5)-(('Per Run Economics'!$B$11*Assumptions!$B$25*A5)+(Assumptions!$B$22+Assumptions!$B$23)))/(D3*A5),0) | E5: =IFERROR(((E3*A5)-(('Per Run Economics'!$B$11*Assumptions!$B$25*A5)+(Assumptions!$B$22+Assumptions!$B$23)))/(E3*A5),0) | F5: =IFERROR(((F3*A5)-(('Per Run Economics'!$B$11*Assumptions!$B$25*A5)+(Assumptions!$B$22+Assumptions!$B$23)))/(F3*A5),0)
A6: 250 | B6: =IFERROR(((B3*A6)-(('Per Run Economics'!$B$11*Assumptions!$B$25*A6)+(Assumptions!$B$22+Assumptions!$B$23)))/(B3*A6),0) | C6: =IFERROR(((C3*A6)-(('Per Run Economics'!$B$11*Assumptions!$B$25*A6)+(Assumptions!$B$22+Assumptions!$B$23)))/(C3*A6),0) | D6: =IFERROR(((D3*A6)-(('Per Run Economics'!$B$11*Assumptions!$B$25*A6)+(Assumptions!$B$22+Assumptions!$B$23)))/(D3*A6),0) | E6: =IFERROR(((E3*A6)-(('Per Run Economics'!$B$11*Assumptions!$B$25*A6)+(Assumptions!$B$22+Assumptions!$B$23)))/(E3*A6),0) | F6: =IFERROR(((F3*A6)-(('Per Run Economics'!$B$11*Assumptions!$B$25*A6)+(Assumptions!$B$22+Assumptions!$B$23)))/(F3*A6),0)
A7: 500 | B7: =IFERROR(((B3*A7)-(('Per Run Economics'!$B$11*Assumptions!$B$25*A7)+(Assumptions!$B$22+Assumptions!$B$23)))/(B3*A7),0) | C7: =IFERROR(((C3*A7)-(('Per Run Economics'!$B$11*Assumptions!$B$25*A7)+(Assumptions!$B$22+Assumptions!$B$23)))/(C3*A7),0) | D7: =IFERROR(((D3*A7)-(('Per Run Economics'!$B$11*Assumptions!$B$25*A7)+(Assumptions!$B$22+Assumptions!$B$23)))/(D3*A7),0) | E7: =IFERROR(((E3*A7)-(('Per Run Economics'!$B$11*Assumptions!$B$25*A7)+(Assumptions!$B$22+Assumptions!$B$23)))/(E3*A7),0) | F7: =IFERROR(((F3*A7)-(('Per Run Economics'!$B$11*Assumptions!$B$25*A7)+(Assumptions!$B$22+Assumptions!$B$23)))/(F3*A7),0)
A8: 1000 | B8: =IFERROR(((B3*A8)-(('Per Run Economics'!$B$11*Assumptions!$B$25*A8)+(Assumptions!$B$22+Assumptions!$B$23)))/(B3*A8),0) | C8: =IFERROR(((C3*A8)-(('Per Run Economics'!$B$11*Assumptions!$B$25*A8)+(Assumptions!$B$22+Assumptions!$B$23)))/(C3*A8),0) | D8: =IFERROR(((D3*A8)-(('Per Run Economics'!$B$11*Assumptions!$B$25*A8)+(Assumptions!$B$22+Assumptions!$B$23)))/(D3*A8),0) | E8: =IFERROR(((E3*A8)-(('Per Run Economics'!$B$11*Assumptions!$B$25*A8)+(Assumptions!$B$22+Assumptions!$B$23)))/(E3*A8),0) | F8: =IFERROR(((F3*A8)-(('Per Run Economics'!$B$11*Assumptions!$B$25*A8)+(Assumptions!$B$22+Assumptions!$B$23)))/(F3*A8),0)

Sheet Method Notes
A1: Method Notes
A3: This model is formula-driven. Change green input cells on the Assumptions sheet.
A4: Exact result cache is based on the 5-minute in-memory cache in backend/services/cache_service.py.
A5: Warm vs cold RAG depends on the 24-hour RAG document TTL in backend/rag/store.py.
A6: Per-run workflow currently includes 3 analyst calls and 1 judge call in backend/workflow.py.
A7: Fresh ticker/day runs add embedding cost, but embeddings are a small share of total variable cost.
A8: FMP is modeled as fixed monthly cost because the code uses plan/quota endpoints, not metered per-call billing.
A9: Retry-heavy cases matter; analysts can retry up to 3x and judge up to 2x.
